enc4ppm/__init__.py
enc4ppm/base_encoder.py
enc4ppm/complex_index_encoder.py
enc4ppm/constants.py
enc4ppm/frequency_encoder.py
enc4ppm/helpers.py
enc4ppm/simple_index_encoder.py
enc4ppm-0.1.8.dist-info/licenses/LICENSE
enc4ppm-0.1.8.dist-info/METADATA
enc4ppm-0.1.8.dist-info/WHEEL
enc4ppm-0.1.8.dist-info/top_level.txt
enc4ppm-0.1.8.dist-info/RECORD
