Metadata-Version: 2.4
Name: enc4ppm
Version: 0.1.8
Summary: Encode logs for predictive process monitoring
Author-email: Riccardo Graziosi <riccardo.graziosi97@gmail.com>
License-Expression: MIT
Project-URL: Homepage, https://github.com/rgraziosi-fbk/enc4ppm
Project-URL: Issues, https://github.com/rgraziosi-fbk/enc4ppm/issues
Classifier: Programming Language :: Python :: 3
Classifier: Operating System :: OS Independent
Requires-Python: >=3.9
License-File: LICENSE
Requires-Dist: pandas
Dynamic: license-file
